django_basemodels_rest/__init__.py
django_basemodels_rest/serializers.py
django_basemodels_rest-0.0.2.dist-info/METADATA
django_basemodels_rest-0.0.2.dist-info/WHEEL
django_basemodels_rest-0.0.2.dist-info/RECORD
