Metadata-Version: 2.4
Name: django-basemodels-rest
Version: 0.0.2
Summary: DRF-интеграция для django-basemodels — готовый сериализатор BaseModel и минимальные утилиты для работы с REST.
Author: skulap
Author-email: skulap01@gmail.com
Requires-Python: >=3.12,<4.0
Classifier: Programming Language :: Python :: 3
Classifier: Programming Language :: Python :: 3.12
Classifier: Programming Language :: Python :: 3.13
Classifier: Programming Language :: Python :: 3.14
Requires-Dist: django-basemodels (>=0.0.4,<0.1.0)
Requires-Dist: djangorestframework (>=3.16.1,<4.0.0)
